{"objects": [
        {
            "comment": "// the back of the cornell box",
            "type": "plane",
            "normal": [0.5, 0.1, 1.5],
            "dist": 40,
            "material": {
                "type": "PHONGMATERIAL",
                "shininess": 500,
                "color": [0.7, 0.7, 0.7],
                "special": "CHECKERBOARD"
            }
        },
        {
            "comment": "// the front of the cornell box",
            "type": "plane",
            "normal": [2.0, 0.5, -1],
            "dist": 40,
            "material": {
                "type": "PHONGMATERIAL",
                "shininess": 500,
                "color": [0.7, 0.7, 0.7],
                "special": "CHECKERBOARD"
            }
        },
        {
            "comment": "// the right of the cornell box",
            "type": "plane",
            "normal": [1.5, 0.3, 0.1],
            "dist": 40,
            "material": {
                "type": "PHONGMATERIAL",
                "shininess": 500,
                "color": [0.7, 0.7, 0.7],
                "special": "CHECKERBOARD"
            }
        },
        {
            "comment": "// the left of the cornell box",
            "type": "plane",
            "normal": [-1, 0.5, 0.8],
            "dist": 40,
            "material": {
                "type": "PHONGMATERIAL",
                "shininess": 500,
                "color": [0.7, 0.7, 0.7],
                "special": "CHECKERBOARD"
            }
        },
        {
            "comment": "// the top of the cornell box",
            "type": "plane",
            "normal": [0, 1, 0.5],
            "dist": 35,
            "material": {
                "type": "PHONGMATERIAL",
                "shininess": 500,
                "color": [0.7, 0.7, 0.7],
                "special": "CHECKERBOARD"
            }
        },
        {
            "comment": "// the bottom of the cornell box",
            "type": "plane",
            "normal": [0.4, -1, 0.2],
            "dist": 30,
            "material": {
                "type": "PHONGMATERIAL",
                "shininess": 500,
                "color": [0.7, 0.7, 0.7],
                "special": "CHECKERBOARD"
            }
        },

        {
            "comment": "// the mirror sphere",
            "type": "sphere",
            "center": [-4, -22, 20],
            "radius": 4,
            "material": {
                "type": "PHONGMATERIAL",
                "color": [0.2, 20, 0.2],
                "shininess": 1000,
                "specular": [1, 1, 1],
                "reflectivity": 0.8,
                "reflectType": "MIRRORREFLECT"
            }
        },

        {
            "comment": "// the mirror sphere (for reflection)",
            "type": "sphere",
            "center": [0, -22, 20],
            "radius": 10,
            "material": {
                "type": "PHONGMATERIAL",
                "color": [0.2, 0.2, 0.2],
                "shininess": 1000,
                "specular": [1, 1, 1],
                "reflectivity": 0.8,
                "reflectType": "MIRRORREFLECT"
            }
        },

        {
            "comment": "// the mirror sphere (for reflection)",
            "type": "sphere",
            "center": [0, -2, 20],
            "radius": 20,
            "material": {
                "type": "PHONGMATERIAL",
                "color": [0.2, 7, 0.2],
                "shininess": 1000,
                "specular": [1, 1, 1],
                "reflectivity": 0.8,
                "reflectType": "MIRRORREFLECT"
            }
        },

        {
            "comment": "// the mirror sphere (for reflection)",
            "type": "sphere",
            "center": [5, -15, 20],
            "radius": 10,
            "material": {
                "type": "PHONGMATERIAL",
                "color": [0.2, 0.2, 0.2],
                "shininess": 1000,
                "specular": [1, 1, 1],
                "reflectivity": 0.8,
                "reflectType": "MIRRORREFLECT"
            }
        },

        {
            "comment": "// the mirror sphere (for reflection)",
            "type": "sphere",
            "center": [5, 9, 20],
            "radius": 10,
            "material": {
                "type": "PHONGMATERIAL",
                "color": [0.2, 0.2, 0.2],
                "shininess": 1000,
                "specular": [1, 1, 1],
                "reflectivity": 0.8,
                "reflectType": "MIRRORREFLECT"
            }
        },


        {
            "comment": "// the mirror sphere (for reflection)",
            "type": "sphere",
            "center": [15, 20, 20],
            "radius": 20,
            "material": {
                "type": "PHONGMATERIAL",
                "color": [0.2, 0.2, 0.2],
                "shininess": 1000,
                "specular": [1, 1, 1],
                "reflectivity": 0.8,
                "reflectType": "MIRRORREFLECT"
            }
        },
        {
            "comment": "// the glass sphere (for refraction)",
            "type": "sphere",
            "center": [-20, -2, 15],
            "radius": 10,
            "material": {
                "type": "PHONGMATERIAL",
                "color": [0.2, 0.4, 1],
                "shininess": 1000,
                "specular": [1, 1, 1],
                "reflectivity": 1,
                "reflectType": "GLASSREFLECT"
            }
        }

    ],

    "lights": [
        {
            "pos": [-20, 20, 10],
            "color": [1, 1, 1],
            "intensity": 50,
            "attenuate": 1.5
        },
        {
            "pos": [20, 20, 10],
            "color": [1, 1, 1],
            "intensity": 30,
            "attenuate": 2
        },

        {
            "pos": [10, 20, -20],
            "color": [1, 1, 1],
            "intensity": 20,
            "attenuate": 1
        }
    ]
}